st_milvus_connection/__init__.py
st_milvus_connection/connection.py
st_milvus_connection-0.0.4.dist-info/METADATA
st_milvus_connection-0.0.4.dist-info/WHEEL
st_milvus_connection-0.0.4.dist-info/top_level.txt
st_milvus_connection-0.0.4.dist-info/RECORD
