Metadata-Version: 2.1
Name: st-milvus-connection
Version: 0.0.4
Summary: Streamlit Milvus Connection
Author-email: bsenst <bnzn@gmx.net>
Project-URL: Homepage, https://github.com/bsenst/st-milvus-connection
Project-URL: Issues, https://github.com/bsenst/st-milvus-connection/issues
Classifier: Programming Language :: Python :: 3
Classifier: License :: OSI Approved :: MIT License
Classifier: Operating System :: OS Independent
Requires-Python: >=3.10
Requires-Dist: pymilvus >=2.3.3
Requires-Dist: streamlit >=1.29.0
